biobb_radiospineomics/__init__.py
biobb_radiospineomics/radiospineomics/__init__.py
biobb_radiospineomics/radiospineomics/calculateindices.py
biobb_radiospineomics/radiospineomics/calculateshape.py
biobb_radiospineomics/radiospineomics/calculatetextures.py
biobb_radiospineomics/radiospineomics/common.py
biobb_radiospineomics/radiospineomics/template_container.py
biobb_radiospineomics/test/__init__.py
biobb_radiospineomics-1.1.20.dist-info/LICENSE
biobb_radiospineomics-1.1.20.dist-info/METADATA
biobb_radiospineomics-1.1.20.dist-info/WHEEL
biobb_radiospineomics-1.1.20.dist-info/entry_points.txt
biobb_radiospineomics-1.1.20.dist-info/top_level.txt
biobb_radiospineomics-1.1.20.dist-info/RECORD
