Metadata-Version: 2.1
Name: biobb-radiospineomics
Version: 1.1.20
Summary: Biobb_Radiospineomics is a wrapped code for the extraction of conventional IVD features and radiomics from T2-weighted MRI
Home-page: https://github.com/TerMcs/radiospineomics
Author: Biobb developers
Author-email: maria.ferri@bsc.es
Project-URL: Documentation, https://github.com/TerMcs/radiospineomics
Project-URL: Bioexcel, https://bioexcel.eu/
Keywords: Bioinformatics Workflows BioExcel Compatibility
Classifier: Development Status :: 5 - Production/Stable
Classifier: Programming Language :: Python :: 3.8
Classifier: Programming Language :: Python :: 3.9
Classifier: Programming Language :: Python :: 3.10
Classifier: License :: OSI Approved :: Apache Software License
Classifier: Operating System :: MacOS :: MacOS X
Classifier: Operating System :: POSIX
Classifier: Operating System :: Unix
Requires-Python: >=3.8
License-File: LICENSE
Requires-Dist: biobb-common ==4.1.0
